comfy_api_client/__init__.py
comfy_api_client/client.py
comfy_api_client/constants.py
comfy_api_client/utils.py
comfy_api_client-0.1.0.dist-info/METADATA
comfy_api_client-0.1.0.dist-info/WHEEL
comfy_api_client-0.1.0.dist-info/RECORD
